classic/messaging/__init__.py
classic/messaging/message.py
classic/messaging/publisher.py
classic/messaging/utils.py
classic_messaging-0.0.2.dist-info/LICENSE
classic_messaging-0.0.2.dist-info/METADATA
classic_messaging-0.0.2.dist-info/WHEEL
classic_messaging-0.0.2.dist-info/top_level.txt
classic_messaging-0.0.2.dist-info/RECORD
