Metadata-Version: 2.1
Name: classic-messaging
Version: 0.0.2
Summary: Provides abstract classes for messages publication in async queues
Home-page: https://github.com/variasov/classic_messaging
Author: Sergei Variasov
Author-email: variasov@gmail.com
License: UNKNOWN
Project-URL: Bug Tracker, https://github.com/variasov/classic_messaging/issues
Platform: UNKNOWN
Classifier: Programming Language :: Python :: 3.7
Classifier: License :: OSI Approved :: MIT License
Classifier: Operating System :: OS Independent
Classifier: Development Status :: 4 - Beta
Requires-Python: >=3.7
License-File: LICENSE
Requires-Dist: attrs (~=21.2.0)
Requires-Dist: classic-components (~=0.0.1)
Provides-Extra: dev
Requires-Dist: pytest (~=6.2.5) ; extra == 'dev'
Requires-Dist: pytest-cov (~=2.12.1) ; extra == 'dev'
Requires-Dist: twine (~=3.4.2) ; extra == 'dev'
Requires-Dist: build (~=0.7.0) ; extra == 'dev'
